json_checker/__init__.py
json_checker/app.py
json_checker/core/__init__.py
json_checker/core/base.py
json_checker/core/checkers.py
json_checker/core/exceptions.py
json_checker/core/reports.py
tests/__init__.py
tests/test_checker.py
tests/core/__init__.py
tests/core/test_report.py
tests/core/checkers/__init__.py
tests/core/checkers/test_and.py
tests/core/checkers/test_dict_checker.py
tests/core/checkers/test_function_checker.py
tests/core/checkers/test_list_checker.py
tests/core/checkers/test_optional_key.py
tests/core/checkers/test_or.py
tests/core/checkers/test_type_checker.py
tests/core/checkers/test_validator.py
json_checker-2.0.0.dist-info/LICENSE
json_checker-2.0.0.dist-info/METADATA
json_checker-2.0.0.dist-info/WHEEL
json_checker-2.0.0.dist-info/top_level.txt
json_checker-2.0.0.dist-info/RECORD
