Metadata-Version: 2.1
Name: json-checker
Version: 2.0.0
Summary: Simple schema validation library
Home-page: https://github.com/DKorytkin/json_checker
Author: Denis Korytkin
Author-email: dkorytkin@gmail.com
License: MIT license
Keywords: Json checker,API testing,requests testing,json schema validation
Platform: linux
Classifier: Development Status :: 5 - Production/Stable
Classifier: Programming Language :: Python :: 3.6
Classifier: Programming Language :: Python :: 3.7
Classifier: Programming Language :: Python :: 3.8
Classifier: Topic :: Software Development :: Libraries
Classifier: Topic :: Software Development :: Testing
Classifier: Topic :: Software Development :: Quality Assurance
Classifier: Topic :: Utilities
Classifier: License :: OSI Approved :: MIT License
Requires-Python: >=3.6
